{
  
  "Scene1": {
    "GameObject_0": {
      "name": "ROOT",
      "active_go": true,
      "uid": 1355249013,
      "parent_uid": 0,
      "Component_0": {
        "active_comp": true,
        "type": 0,
        "TRANSFORM": [ 0.0, 0.0, 0.0, 0.0, 0.0, 0.0, 1.0, 1.0, 1.0, 1.0 ]
      }
    },
    "GameObject_1": {
      "name": "BakerHouse.fbx",
      "active_go": true,
      "uid": 1355248013,
      "parent_uid": 1355249013,
      "Component_0": {
        "active_comp": true,
        "type": 0,
        "TRANSFORM": [ 0.0, 0.0, 0.0, 0.0, 0.0, 0.0, 1.0, 1.0, 1.0, 1.0 ]
      },
      "Component_1": {
        "active_comp": true,
        "type": 2,
        "MATERIAL": {
          "path": "D:\\Documents\\GitHub\\3DEngine18\\Game\\Assets\\Textures\\Baker_house.png",
          "id": 3,
          "heigh": 1024,
          "width": 1024
        }
      }
    },
    "GameObject_1_0": {
      "name": "Chimney",
      "active_go": true,
      "uid": 1041705475,
      "parent_uid": 1355248013,
      "Component_0": {
        "active_comp": true,
        "type": 0,
        "TRANSFORM": [ 0.0, 0.0, 0.0, -0.7071068286895752, 0.0, 0.0, 0.7071067094802856, 100.0, 100.0, 100.0 ]
      },
      "Component_1": {
        "active_comp": true,
        "type": 1,
        "MESH": "Assets/Models/BakerHouse/Chimney.lw"
      },
      "Component_2": {
        "active_comp": true,
        "type": 2,
        "MATERIAL": {
          "path": "D:\\Documents\\GitHub\\3DEngine18\\Game\\Assets\\Textures\\Baker_house.png",
          "id": 3,
          "heigh": 1024,
          "width": 1024
        }
      }
    },
    "GameObject_1_1": {
      "name": "Baker_house",
      "active_go": true,
      "uid": 111314419,
      "parent_uid": 1355248013,
      "Component_0": {
        "active_comp": true,
        "type": 0,
        "TRANSFORM": [ 0.0, 0.0, 0.0, -0.7071068286895752, 0.0, 0.0, 0.7071067094802856, 100.0, 100.0, 100.0 ]
      },
      "Component_1": {
        "active_comp": true,
        "type": 1,
        "MESH": "Assets/Models/BakerHouse/Baker_house.lw"
      },
      "Component_2": {
        "active_comp": true,
        "type": 2,
        "MATERIAL": {
          "path": "D:\\Documents\\GitHub\\3DEngine18\\Game\\Assets\\Textures\\Baker_house.png",
          "id": 3,
          "heigh": 1024,
          "width": 1024
        }
      }
    }
  }
}